CHANGELOG.rst
MANIFEST.in
README.rst
setup.py
fileNameTranslation/__init__.py
fileNameTranslation/__main__.py
fileNameTranslation/__version__.py
fileNameTranslation/options.py
fileNameTranslation.egg-info/PKG-INFO
fileNameTranslation.egg-info/SOURCES.txt
fileNameTranslation.egg-info/dependency_links.txt
fileNameTranslation.egg-info/entry_points.txt
fileNameTranslation.egg-info/requires.txt
fileNameTranslation.egg-info/top_level.txt
fileNameTranslation.egg-info/zip-safe