Metadata-Version: 1.1
Name: fileNameTranslation
Version: 0.1
Summary: This package will allow you to translate your file names to you desire language
Home-page: https://github.com/aviadlevy/fileNameTranslation/
Author: Aviad Levy
Author-email: aviadlevy1@gmail.com
License: LGPLv3
Platform: UNKNOWN
Classifier: Development Status :: 2 - Pre-Alpha
Classifier: License :: OSI Approved :: GNU Library or Lesser General Public License (LGPL)
Classifier: Operating System :: OS Independent
Classifier: Intended Audience :: End Users/Desktop
Classifier: Programming Language :: Python :: 2.7
Classifier: Topic :: Desktop Environment :: File Managers
